nsrr/__init__.py
nsrr/__main__.py
nsrr/nsrr.py
nsrr-0.2.0.dist-info/METADATA
nsrr-0.2.0.dist-info/WHEEL
nsrr-0.2.0.dist-info/entry_points.txt
nsrr-0.2.0.dist-info/top_level.txt
nsrr-0.2.0.dist-info/RECORD
