Metadata-Version: 2.1
Name: nsrr
Version: 0.2.0
Summary: Access Sleep research resources from Sleepdata.org
Home-page: https://github.com/nsrr/nsrr-cloud/tree/master/client-lib/pypi
Author: Shyamal
Author-email: sagarwal12@bwh.harvard.edu
License: MIT
Platform: UNKNOWN
Classifier: License :: OSI Approved :: MIT License
Classifier: Programming Language :: Python :: 3
Requires-Dist: requests
Requires-Dist: pandas
